
{
  "build": {
    "development": {
      "developmentClient": true,
      "distribution": "internal",
      "android": {
        "buildType": "apk",
        "gradleCommand": ":app:assembleDebug"
      },
      "ios": {
        "simulator": true
      },
      "env": {
        "GRADLE_OPTS": "-Xmx10240m -XX:MaxMetaspaceSize=5120m -XX:ReservedCodeCacheSize=1536m -XX:+HeapDumpOnOutOfMemoryError -XX:+UseG1GC"
      }
    },
    "preview": {
      "distribution": "internal",
      "android": {
        "buildType": "apk",
        "withoutCredentials": true
      },
      "env": {
        "GRADLE_OPTS": "-Xmx10240m -XX:MaxMetaspaceSize=5120m -XX:ReservedCodeCacheSize=1536m -XX:+HeapDumpOnOutOfMemoryError -XX:+UseG1GC"
      }
    },
    "production": {
      "android": {
        "buildType": "apk"
      },
      "env": {
        "GRADLE_OPTS": "-Xmx12288m -XX:MaxMetaspaceSize=6144m -XX:ReservedCodeCacheSize=2048m -XX:+HeapDumpOnOutOfMemoryError -XX:+UseG1GC -XX:MaxGCPauseMillis=200",
        "ORG_GRADLE_PROJECT_kotlin.daemon.jvmargs": "-Xmx8192m -XX:MaxMetaspaceSize=4096m -XX:ReservedCodeCacheSize=1536m"
      }
    },
    "production-aab": {
      "android": {
        "buildType": "app-bundle"
      },
      "env": {
        "GRADLE_OPTS": "-Xmx12288m -XX:MaxMetaspaceSize=6144m -XX:ReservedCodeCacheSize=2048m -XX:+HeapDumpOnOutOfMemoryError -XX:+UseG1GC -XX:MaxGCPauseMillis=200",
        "ORG_GRADLE_PROJECT_kotlin.daemon.jvmargs": "-Xmx8192m -XX:MaxMetaspaceSize=4096m -XX:ReservedCodeCacheSize=1536m"
      }
    }
  },
  "submit": {
    "production": {}
  }
}
